kermi2mqtt/__init__.py
kermi2mqtt/__main__.py
kermi2mqtt/bridge.py
kermi2mqtt/config.py
kermi2mqtt/ha_discovery.py
kermi2mqtt/http_client.py
kermi2mqtt/mappings.py
kermi2mqtt/modbus_client.py
kermi2mqtt/mqtt_client.py
kermi2mqtt/safety.py
kermi2mqtt/models/__init__.py
kermi2mqtt/models/datapoint.py
kermi2mqtt/models/device.py
kermi2mqtt-0.1.2.dist-info/licenses/LICENSE
kermi2mqtt-0.1.2.dist-info/METADATA
kermi2mqtt-0.1.2.dist-info/WHEEL
kermi2mqtt-0.1.2.dist-info/entry_points.txt
kermi2mqtt-0.1.2.dist-info/top_level.txt
kermi2mqtt-0.1.2.dist-info/RECORD
