Metadata-Version: 2.4
Name: kermi2mqtt
Version: 0.1.2
Summary: Kermi x-center to MQTT bridge for heat pumps with Home Assistant auto-discovery
Author: kermi2mqtt contributors
License: Apache-2.0
Project-URL: Homepage, https://github.com/jr42/kermi2mqtt
Project-URL: Repository, https://github.com/jr42/kermi2mqtt
Project-URL: Issues, https://github.com/jr42/kermi2mqtt/issues
Keywords: kermi,heat-pump,modbus,mqtt,home-assistant,iot,http
Classifier: Development Status :: 3 - Alpha
Classifier: Intended Audience :: End Users/Desktop
Classifier: License :: OSI Approved :: Apache Software License
Classifier: Programming Language :: Python :: 3
Classifier: Programming Language :: Python :: 3.12
Classifier: Programming Language :: Python :: 3.13
Classifier: Programming Language :: Python :: 3.14
Classifier: Topic :: Home Automation
Classifier: Topic :: System :: Hardware :: Hardware Drivers
Requires-Python: >=3.12
License-File: LICENSE
Requires-Dist: kermi-xcenter>=0.3.0
Requires-Dist: aiomqtt>=2.0.0
Requires-Dist: pydantic>=2.0.0
Requires-Dist: pyyaml>=6.0.0
Provides-Extra: dev
Requires-Dist: pytest>=8.0.0; extra == "dev"
Requires-Dist: pytest-asyncio>=0.23.0; extra == "dev"
Requires-Dist: pytest-mock>=3.12.0; extra == "dev"
Requires-Dist: pytest-cov>=4.0.0; extra == "dev"
Requires-Dist: ruff>=0.1.0; extra == "dev"
Requires-Dist: mypy>=1.8.0; extra == "dev"
Requires-Dist: types-PyYAML>=6.0.0; extra == "dev"
Dynamic: license-file
